{
    "boolean-True":  "Igaz",
    "boolean-False":  "Hamis",
    "confirmation-ok":  "Rendben",
    "confirmation-cancel":  "Törlés",
    "confirmation-yes":  "Igen",
    "confirmation-no":  "Nem",
    "confirmation-ignore":  "Figyelmen kívül hagyás",
    "confirmation-retry":  "Újrapróbálkozás",
    "confirmation-delete":  "Törlés",
    "confirmation-abort":  "Megszakítás",
    "confirmation-export":  "Export",
    "confirmation-import":  "Import",
    "confirmation-confirm":  "Megerősítse",
    "confirmation-confirmation":  "Megerősítés",
    "confirmation-information":  "Információk",
    "confirmation-default-message":  "Biztos vagy benne, hogy ezt a mozdulatot akarod végrehajtani?",
    "confirmation-invalid-syntax":  "Érvénytelen szintaxis.",
    "confirmation-try-again":  "Kérlek, próbáld meg újra.",
    "datetime-months-abbr-0":  "Jan",
    "datetime-months-full-0":  "Január",
    "datetime-months-abbr-1":  "Feb",
    "datetime-months-full-1":  "Február",
    "datetime-months-abbr-2":  "Mar",
    "datetime-months-full-2":  "Március",
    "datetime-months-abbr-3":  "Apr",
    "datetime-months-full-3":  "Április",
    "datetime-months-abbr-4":  "Május",
    "datetime-months-full-4":  "Május",
    "datetime-months-abbr-5":  "Jun",
    "datetime-months-full-5":  "Június",
    "datetime-months-abbr-6":  "Július",
    "datetime-months-full-6":  "Július",
    "datetime-months-abbr-7":  "Augusztus",
    "datetime-months-full-7":  "Augusztus",
    "datetime-months-abbr-8":  "Szep",
    "datetime-months-full-8":  "Szeptember",
    "datetime-months-abbr-9":  "Október",
    "datetime-months-full-9":  "Október",
    "datetime-months-abbr-10":  "Nov",
    "datetime-months-full-10":  "November",
    "datetime-months-abbr-11":  "Dec",
    "datetime-months-full-11":  "December",
    "datetime-days-abbr-0":  "Mon",
    "datetime-days-full-0":  "Hétfő",
    "datetime-days-abbr-1":  "Kedd",
    "datetime-days-full-1":  "Kedd",
    "datetime-days-abbr-2":  "Szerda",
    "datetime-days-full-2":  "Szerda",
    "datetime-days-abbr-3":  "Csütörtök",
    "datetime-days-full-3":  "Csütörtök",
    "datetime-days-abbr-4":  "Péntek",
    "datetime-days-full-4":  "Péntek",
    "datetime-days-abbr-5":  "Szombat",
    "datetime-days-full-5":  "Szombat",
    "datetime-days-abbr-6":  "Sun",
    "datetime-days-full-6":  "Vasárnap"
}
